[
  {
    "pricing_key": "hvac_flex_duct_6",
    "item_name": "Flex Duct 6\" 25ft",
    "unit": "each",
    "type": "MATERIAL",
    "syncable": "YES",
    "notes": "",
    "search_query": "homedepot.com master flow 6 in x 25 ft insulated flexible duct r-6",
    "hd_url": "https://www.homedepot.com/p/Master-Flow-6-in-x-25-ft-Insulated-Flexible-Duct-R6-Silver-Jacket-F6IFD6X300/100396935",
    "item_id": "100396935",
    "match_title": "6 in. x 25 ft. Insulated Flexible Duct R6 Silver Jacket",
    "match_price": null,
    "price_unit": "each",
    "confidence": "high",
    "haiku_reason": "Product is a 6-inch flexible duct in 25-foot length, matching the target item specifications exactly.",
    "haiku_matches": true,
    "error": null,
    "source": "web_search"
  },
  {
    "pricing_key": "hvac_flex_duct_8",
    "item_name": "Flex Duct 8\" 25ft",
    "unit": "each",
    "type": "MATERIAL",
    "syncable": "YES",
    "notes": "",
    "search_query": "homedepot.com master flow 8 in x 25 ft insulated flexible duct r-6",
    "hd_url": "https://www.homedepot.com/p/Master-Flow-8-in-x-25-ft-Insulated-Flexible-Duct-R8-Silver-Jacket-F8IFD8X300/202562741",
    "item_id": "202562741",
    "match_title": "Master Flow - 8 in. x 25 ft. Insulated Flexible Duct R8 Silver Jacket",
    "match_price": null,
    "price_unit": "each",
    "confidence": "high",
    "haiku_reason": "Product is an 8-inch by 25-foot flexible duct matching the target specifications exactly.",
    "haiku_matches": true,
    "error": null,
    "source": "web_search"
  },
  {
    "pricing_key": "hvac_rigid_duct_lf",
    "item_name": "Rigid Sheet Metal Duct",
    "unit": "lf",
    "type": "MATERIAL",
    "syncable": "PARTIAL",
    "notes": "Often custom fab",
    "search_query": "homedepot.com master flow 6 in x 5 ft galvanized round sheet metal duct",
    "hd_url": "https://www.homedepot.com/p/Master-Flow-6-in-x-5-ft-Round-Metal-Duct-Pipe-CP6X60/100125106",
    "item_id": "100125106",
    "match_title": "Master Flow 6 in. x 5 ft. Round Metal Duct Pipe CP6X60",
    "match_price": null,
    "price_unit": "lf",
    "confidence": "medium",
    "haiku_reason": "This is a rigid sheet metal duct pipe in round configuration, sold by the linear foot (5 ft length), matching the target material type.",
    "haiku_matches": true,
    "error": null,
    "source": "web_search"
  },
  {
    "pricing_key": "hvac_duct_insulation",
    "item_name": "Duct Insulation Wrap",
    "unit": "roll",
    "type": "MATERIAL",
    "syncable": "YES",
    "notes": "",
    "search_query": "homedepot.com owens corning duct wrap insulation r-6 fiberglass roll",
    "hd_url": "https://www.homedepot.com/p/Everbilt-R6-6-in-Ductwork-Insulation-Sleeve-INSLV6/334147823",
    "item_id": "334147823",
    "match_title": "Everbilt - R6 6 in. Ductwork Insulation Sleeve",
    "match_price": null,
    "price_unit": "roll",
    "confidence": "medium",
    "haiku_reason": "Product is a ductwork insulation sleeve sold as a roll, matching the target item description for duct insulation wrap.",
    "haiku_matches": true,
    "error": null,
    "source": "web_search"
  },
  {
    "pricing_key": "hvac_duct_tape",
    "item_name": "Duct Tape (HVAC rated)",
    "unit": "roll",
    "type": "MATERIAL",
    "syncable": "YES",
    "notes": "",
    "search_query": "homedepot.com nashua 557 ul 181b-fx hvac foil tape 60 yd roll",
    "hd_url": "https://www.homedepot.com/p/Nashua-Tape-1-89-in-x-60-yd-557-Pro-Grade-UL-Listed-Duct-Tape-1542699/100208576?MERCH=REC-_-pip_alternatives-_-205033915-_-16-_-n/a-_-n/a-_-n/a-_-n/a-_-n/a",
    "item_id": "100208576",
    "match_title": "1.89 in. x 60 yd. 557 Pro-Grade UL Listed Duct Tape",
    "match_price": null,
    "price_unit": "roll",
    "confidence": "high",
    "haiku_reason": "UL Listed duct tape specifically approved for HVAC duct sealing (class 1 flexible duct joints per UL code), sold as a roll.",
    "haiku_matches": true,
    "error": null,
    "source": "web_search"
  },
  {
    "pricing_key": "hvac_line_set",
    "item_name": "Copper Line Set 25ft",
    "unit": "each",
    "type": "MATERIAL",
    "syncable": "YES",
    "notes": "1/4\" + 3/8\" insulated",
    "search_query": "homedepot.com mrcool 1/4 in x 3/8 in x 25 ft insulated copper line set mini split",
    "hd_url": "https://www.homedepot.com/p/MRCOOL-25-ft-1-4-in-x-3-8-in-Flared-Line-Set-Kit-with-Communication-Wire-Wall-Sleeve-and-Drain-Hose-MC25-1438/312540649",
    "item_id": "312540649",
    "match_title": "MRCOOL - 25 ft. 1/4 in. x 3/8 in. Flared Line Set Kit with Communication Wire Wall Sleeve and Drain Hose",
    "match_price": null,
    "price_unit": "each",
    "confidence": "high",
    "haiku_reason": "Product is a 25 ft copper line set with 1/4\" and 3/8\" insulated lines, matching the target specifications exactly.",
    "haiku_matches": true,
    "error": null,
    "source": "web_search"
  },
  {
    "pricing_key": "hvac_condensate_pump",
    "item_name": "Condensate Pump",
    "unit": "each",
    "type": "MATERIAL",
    "syncable": "YES",
    "notes": "",
    "search_query": "homedepot.com little giant vcma-15uls 115v automatic condensate removal pump",
    "hd_url": "https://www.homedepot.com/p/Little-Giant-115-Volt-Condensate-Removal-Pump-VCMA-15ULST/324224438",
    "item_id": "324224438",
    "match_title": "Little Giant 115-Volt Condensate Removal Pump VCMA-15ULST",
    "match_price": null,
    "price_unit": "each",
    "confidence": "high",
    "haiku_reason": "Product is a condensate removal pump sold as a single unit, matching the target item description.",
    "haiku_matches": true,
    "error": null,
    "source": "web_search"
  },
  {
    "pricing_key": "hvac_disconnect",
    "item_name": "Disconnect Box 60A",
    "unit": "each",
    "type": "MATERIAL",
    "syncable": "YES",
    "notes": "Required by code",
    "search_query": "homedepot.com square d 60 amp 240-volt non-fused ac disconnect",
    "hd_url": "https://www.homedepot.com/p/Square-D-QO-60-Amp-240-Volt-7-4-kW-Non-Fuse-AC-Disconnect-QO200TRCP-QO200TRCP/329864804",
    "item_id": "329864804",
    "match_title": "QO 60 Amp 240-Volt 7.4 kW Non-Fuse AC Disconnect(QO200TRCP)",
    "match_price": null,
    "price_unit": "each",
    "confidence": "medium",
    "haiku_reason": "Product is a 60A disconnect switch, which matches the target 'Disconnect Box 60A' specification.",
    "haiku_matches": true,
    "error": null,
    "source": "web_search"
  },
  {
    "pricing_key": "hvac_pad",
    "item_name": "AC Pad/Stand",
    "unit": "each",
    "type": "MATERIAL",
    "syncable": "YES",
    "notes": "Condenser unit base",
    "search_query": "homedepot.com diversitech 32 in x 32 in x 3 in plastic equipment pad",
    "hd_url": "https://www.homedepot.com/p/Diversitech-E-Lite-32-in-W-x-32-in-D-x-3-in-H-Plastic-HVAC-Condensor-Pad-EL3232-3/334530867",
    "item_id": "334530867",
    "match_title": "E-Lite 32 in. W x 32 in. D x 3 in. H Plastic HVAC Condensor Pad",
    "match_price": null,
    "price_unit": "each",
    "confidence": "high",
    "haiku_reason": "Product is a plastic HVAC condenser pad designed as a base for AC condenser units, matching the target item description.",
    "haiku_matches": true,
    "error": null,
    "source": "web_search"
  },
  {
    "pricing_key": "hvac_thermostat_wire",
    "item_name": "Thermostat Wire 18/5 250ft",
    "unit": "roll",
    "type": "MATERIAL",
    "syncable": "YES",
    "notes": "",
    "search_query": "homedepot.com southwire 18/5 thermostat wire 250 ft solid copper",
    "hd_url": "https://www.homedepot.com/p/Southwire-250-ft-18-5-Brown-Solid-CU-CL2-Thermostat-Wire-64169644/202316418",
    "item_id": "202316418",
    "match_title": "250 ft. 18/5 Brown Solid CU CL2 Thermostat Wire",
    "match_price": null,
    "price_unit": "roll",
    "confidence": "high",
    "haiku_reason": "Product is 18/5 thermostat wire in 250 ft roll, matching target specifications exactly.",
    "haiku_matches": true,
    "error": null,
    "source": "web_search"
  },
  {
    "pricing_key": "hvac_dryer_vent",
    "item_name": "Dryer Vent Kit",
    "unit": "kit",
    "type": "MATERIAL",
    "syncable": "YES",
    "notes": "",
    "search_query": "homedepot.com everbilt 4 in dryer vent installation kit periscope hood clamps",
    "hd_url": "https://www.homedepot.com/p/Everbilt-4-in-x-8-ft-Dryer-Vent-Kit-with-Guard-TD48PGKHD6/203626523",
    "item_id": "203626523",
    "match_title": "Everbilt 4 in. x 8 ft. Dryer Vent Kit with Guard TD48PGKHD6",
    "match_price": null,
    "price_unit": "kit",
    "confidence": "high",
    "haiku_reason": "Product is a complete dryer vent kit with hood, duct, and clamps matching the target item description.",
    "haiku_matches": true,
    "error": null,
    "source": "web_search"
  }
]